dataset_processor/__init__.py
dataset_processor/data.py
dataset_processor/filter.py
dataset_processor/processor.py
dataset_processor/uitl.py
dataset_processor/tools/__init__.py
dataset_processor/tools/tagger.py
dataset_processor/tools/upscale.py
dataset_processor-0.3.0.data/data/conf/conf.yaml
dataset_processor-0.3.0.data/data/doc/doc_cn.md
dataset_processor-0.3.0.dist-info/LICENSE
dataset_processor-0.3.0.dist-info/METADATA
dataset_processor-0.3.0.dist-info/WHEEL
dataset_processor-0.3.0.dist-info/top_level.txt
dataset_processor-0.3.0.dist-info/RECORD
